peepdf/JSAnalysis.py
peepdf/PDFConsole.py
peepdf/PDFCore.py
peepdf/PDFCrypto.py
peepdf/PDFFilters.py
peepdf/PDFUtils.py
peepdf/__init__.py
peepdf/aes.py
peepdf/ccitt.py
peepdf/jjdecode.py
peepdf/lzw.py
peepdf/main.py
peepdf_fork-0.4.3.dist-info/AUTHORS
peepdf_fork-0.4.3.dist-info/COPYING
peepdf_fork-0.4.3.dist-info/METADATA
peepdf_fork-0.4.3.dist-info/WHEEL
peepdf_fork-0.4.3.dist-info/entry_points.txt
peepdf_fork-0.4.3.dist-info/top_level.txt
peepdf_fork-0.4.3.dist-info/RECORD
