Metadata-Version: 2.1
Name: peepdf-fork
Version: 0.4.3
Summary: UNKNOWN
Home-page: http://eternal-todo.com
Author: Jose Miguel Esparza
Author-email: UNKNOWN
License: GNU GPLv3
Platform: UNKNOWN
Requires-Dist: jsbeautifier (>=1.6.2)
Requires-Dist: colorama (>=0.3.7)
Requires-Dist: future (>=0.16.0)
Requires-Dist: Pillow (>=3.2.0)
Requires-Dist: pythonaes (>=1.0)
